NO-11/moore/11_non.v
module moore_110110(input  clk, rst, x, output reg z);
  parameter A= 4'h1;
  parameter B= 4'h2;
  parameter C= 4'h3;
  parameter D= 4'h4;
  parameter E= 4'h5;
  parameter F= 4'h6; 
  parameter G=4'h7;  
  output reg [3:0] state, next_state;
  always @(posedge clk or negedge rst) begin
    if(!rst) begin 
      state <= A;
    end
    else state <= next_state;
  end
  
  always @(state or x) begin
    case(state)
      A: begin
	     
           if(x ==1) next_state = B;
           else       next_state = A;
         end
      B: begin
           if(x == 1) next_state = C;
           else       next_state = A;
         end
      C: begin
           if(x == 0) next_state = D;
           else       next_state = A;
         end
      D: begin
           if(x == 1) next_state = E;
           else       next_state = A;
         end
      E: begin
           if(x == 1) next_state = F;
           else       next_state = A; 
         end
      F: begin
	      if(x==0)next_state = G;
	      else   next_state = B;
        end
    G:begin 
            
             if(x==0)next_state=A;
             else next_state=B;
         end 

      default: next_state = A;
    endcase
  end
  initial begin
  if(state==G)
  assign z =1;
else 
	z=0;
end
endmodule

NO-11/moore/11_non_tb.v
module moore_110110_tb;
  reg clk, rst, x;
  wire z;
  
  moore_110110 dut(clk, rst, x, z);
  initial clk = 0;   
  always #5 clk = ~clk;
    
  initial begin
    x = 0;
    #1 rst = 0;
    #2 rst = 1;
    
    #3 x = 1;
    #4 x = 1;
    #4 x = 0;
    #4 x = 1;
    #6 x = 1;
    #7 x = 1;
    #6 x = 0;
    #6 x = 1;
    #6 x = 1;
    #6 x = 0;
    #6 x = 0;
    
    #4 x = 1;
    #4 x = 0;
    #5 x = 1;
    #6 x = 1;
    #6 x = 1;
    #6 x = 0;
    #6 x = 1;
    #6 x = 1;
    #6 x = 0;
    #5 x = 0;

    #100;
    $finish;
    $monitor("%0t: x = %0b, z = %0b", $time, x, z);

  end
  
  initial begin
    
    $dumpfile("moore_110110.vcd");
    $dumpvars(0);
  end
endmodule

NO-11/moore/moore_110110.vcd
$date
	Sat Feb 25 14:19:05 2023
$end
$version
	Icarus Verilog
$end
$timescale
	1s
$end
$scope module moore_110110_tb $end
$var wire 1 ! z $end
$var reg 1 " clk $end
$var reg 1 # rst $end
$var reg 1 $ x $end
$scope module dut $end
$var wire 1 " clk $end
$var wire 1 # rst $end
$var wire 1 $ x $end
$var reg 4 % next_state [3:0] $end
$var reg 4 & state [3:0] $end
$var reg 1 ! z $end
$upscope $end
$upscope $end
$enddefinitions $end
#0
$dumpvars
bx &
b1 %
0$
x#
0"
0!
$end
#1
b1 &
0#
#3
1#
#5
1"
#6
b10 %
1$
#10
0"
#14
b1 %
0$
#15
1"
#18
b10 %
1$
#20
0"
#25
b11 %
b10 &
1"
#30
0"
#35
b1 %
b11 &
1"
#37
b100 %
0$
#40
0"
#43
b1 %
1$
#45
b10 %
b1 &
1"
#50
0"
#55
b1 %
1"
0$
#60
0"
#65
b10 %
1$
1"
#69
b1 %
0$
#70
0"
#74
b10 %
1$
#75
b11 %
b10 &
1"
#80
0"
#85
b1 %
b11 &
1"
#90
0"
#92
b100 %
0$
#95
b1 %
b100 &
1"
#98
b101 %
1$
#100
0"
#105
b110 %
b101 &
1"
#110
b1 %
0"
0$
#115
b1 &
1"
